terris/__init__.py
terris/__main__.py
terris-0.0.0.dist-info/LICENSE
terris-0.0.0.dist-info/METADATA
terris-0.0.0.dist-info/WHEEL
terris-0.0.0.dist-info/top_level.txt
terris-0.0.0.dist-info/RECORD
